boldi/_dev_version.py
boldi/dev.py
boldi_dev-0.9.7.dist-info/METADATA
boldi_dev-0.9.7.dist-info/WHEEL
boldi_dev-0.9.7.dist-info/entry_points.txt
boldi_dev-0.9.7.dist-info/RECORD
