Metadata-Version: 2.4
Name: boldi-dev
Version: 0.9.7
Summary: boldi.dev part of Boldi's Python libraries
Author-email: Boldizsár Palotás <boldizsar.palotas@gmail.com>
License: MIT
Requires-Python: >=3.12
Requires-Dist: boldi-cli==0.9.7
Requires-Dist: boldi-ctx==0.9.7
Requires-Dist: mdx-truly-sane-lists
Requires-Dist: mkdocs-autorefs
Requires-Dist: mkdocs-material
Requires-Dist: mkdocstrings[python]
Requires-Dist: mypy
Requires-Dist: ruff
